[
  {
    "month": "January",
    "element": "AI Planning & Setup",
    "task": "Understand business goals and decide where AI will be used on the website, such as recommendations, chat support, and insights",
    "monthlyTask": "One-time planning and documentation",
    "monthlyQuantifiable": "No",
    "team": "artificial-intelligence"
  },
  {
    "month": "January",
    "element": "AI Planning & Setup",
    "task": "Review product, customer, and order data and prepare it for AI usage",
    "monthlyTask": "One-time data review and cleanup",
    "monthlyQuantifiable": "No",
    "team": "artificial-intelligence"
  },
  {
    "month": "January",
    "element": "AI Planning & Setup",
    "task": "Define basic rules to ensure AI responses stay accurate and brand-safe",
    "monthlyTask": "One-time rule definition",
    "monthlyQuantifiable": "No",
    "team": "artificial-intelligence"
  },

  {
    "month": "February",
    "element": "Custom Kit Builder",
    "task": "Create logic to recommend product kits based on skin type, concerns, and preferences",
    "monthlyTask": "Initial setup of recommendation rules",
    "monthlyQuantifiable": "No",
    "team": "artificial-intelligence"
  },
  {
    "month": "February",
    "element": "Custom Kit Builder",
    "task": "Test product kit suggestions across different customer scenarios",
    "monthlyTask": "Test 10–15 scenarios",
    "monthlyQuantifiable": "Yes",
    "team": "artificial-intelligence"
  },

  {
    "month": "March",
    "element": "Custom Kit Builder",
    "task": "Improve kit recommendations using customer feedback and usage data",
    "monthlyTask": "Monthly review and updates",
    "monthlyQuantifiable": "Yes",
    "team": "artificial-intelligence"
  },
  {
    "month": "March",
    "element": "Custom Kit Builder",
    "task": "Fix incorrect or confusing recommendations reported by users",
    "monthlyTask": "NA",
    "monthlyQuantifiable": "NA",
    "team": "artificial-intelligence"
  },

  {
    "month": "April",
    "element": "AI Chat Assistant",
    "task": "Train the chat assistant using product details, ingredients, and Ayurvedic information",
    "monthlyTask": "One-time training and setup",
    "monthlyQuantifiable": "No",
    "team": "artificial-intelligence"
  },
  {
    "month": "April",
    "element": "AI Chat Assistant",
    "task": "Define what the assistant can answer and when it should escalate to human support",
    "monthlyTask": "One-time configuration",
    "monthlyQuantifiable": "No",
    "team": "artificial-intelligence"
  },

  {
    "month": "May",
    "element": "AI Chat Assistant",
    "task": "Review chat conversations to improve accuracy and clarity of responses",
    "monthlyTask": "Review 50–100 conversations",
    "monthlyQuantifiable": "Yes",
    "team": "artificial-intelligence"
  },
  {
    "month": "May",
    "element": "AI Chat Assistant",
    "task": "Update responses based on new products or customer questions",
    "monthlyTask": "NA",
    "monthlyQuantifiable": "NA",
    "team": "artificial-intelligence"
  },

  {
    "month": "June",
    "element": "Customer Intelligence",
    "task": "Track how users browse, interact, and purchase on the website",
    "monthlyTask": "Monthly dashboard review",
    "monthlyQuantifiable": "Yes",
    "team": "artificial-intelligence"
  },
  {
    "month": "June",
    "element": "Customer Intelligence",
    "task": "Identify common drop-off points in the customer journey",
    "monthlyTask": "Monthly analysis",
    "monthlyQuantifiable": "Yes",
    "team": "artificial-intelligence"
  },

  {
    "month": "July",
    "element": "Customer Intelligence",
    "task": "Group customers into segments such as repeat buyers, new users, and inactive users",
    "monthlyTask": "Update segments monthly",
    "monthlyQuantifiable": "Yes",
    "team": "artificial-intelligence"
  },
  {
    "month": "July",
    "element": "Customer Intelligence",
    "task": "Share customer insights with marketing and website teams",
    "monthlyTask": "Monthly summary",
    "monthlyQuantifiable": "NA",
    "team": "artificial-intelligence"
  },

  {
    "month": "August",
    "element": "Customer Intelligence",
    "task": "Use customer insights to improve recommendations, messaging, and follow-ups",
    "monthlyTask": "NA",
    "monthlyQuantifiable": "NA",
    "team": "artificial-intelligence"
  },
  {
    "month": "August",
    "element": "Customer Intelligence",
    "task": "Review impact of changes made using customer data",
    "monthlyTask": "Monthly review",
    "monthlyQuantifiable": "Yes",
    "team": "artificial-intelligence"
  },

  {
    "month": "September",
    "element": "Demand Forecasting",
    "task": "Review past sales data and seasonal trends to understand demand",
    "monthlyTask": "Monthly sales analysis",
    "monthlyQuantifiable": "Yes",
    "team": "artificial-intelligence"
  },
  {
    "month": "September",
    "element": "Demand Forecasting",
    "task": "Identify fast-moving and slow-moving products",
    "monthlyTask": "Monthly product review",
    "monthlyQuantifiable": "Yes",
    "team": "artificial-intelligence"
  },

  {
    "month": "October",
    "element": "Demand Forecasting",
    "task": "Suggest inventory planning improvements based on demand insights",
    "monthlyTask": "Monthly forecast update",
    "monthlyQuantifiable": "Yes",
    "team": "artificial-intelligence"
  },
  {
    "month": "October",
    "element": "Demand Forecasting",
    "task": "Align demand insights with upcoming offers or promotions",
    "monthlyTask": "NA",
    "monthlyQuantifiable": "NA",
    "team": "artificial-intelligence"
  },

  {
    "month": "November",
    "element": "AI Optimization",
    "task": "Review AI features and improve them to increase conversions and repeat purchases",
    "monthlyTask": "Monthly performance review",
    "monthlyQuantifiable": "Yes",
    "team": "artificial-intelligence"
  },
  {
    "month": "November",
    "element": "AI Optimization",
    "task": "Fix issues or gaps identified during performance reviews",
    "monthlyTask": "NA",
    "monthlyQuantifiable": "NA",
    "team": "artificial-intelligence"
  },

  {
    "month": "December",
    "element": "AI Review & Planning",
    "task": "Review overall AI performance and document learnings from the year",
    "monthlyTask": "One-time annual review",
    "monthlyQuantifiable": "No",
    "team": "artificial-intelligence"
  },
  {
    "month": "December",
    "element": "AI Review & Planning",
    "task": "Plan improvements and new AI features for the next year",
    "monthlyTask": "One-time planning",
    "monthlyQuantifiable": "No",
    "team": "artificial-intelligence"
  }
]
